hop3/.DS_Store
hop3/__init__.py
hop3/alembic/README
hop3/alembic/env.py
hop3/alembic/script.py.mako
hop3/alembic/versions/0d21c362f66d_add_app_state_machine_and_error_message.py
hop3/alembic/versions/961bfd2ecce5_add_runtime_field_to_app_model.py
hop3/alembic/versions/d20dd80dafca_initial_schema.py
hop3/alembic.ini
hop3/commands/__init__.py
hop3/commands/_base.py
hop3/commands/_errors.py
hop3/commands/admin.py
hop3/commands/app.py
hop3/commands/apps.py
hop3/commands/auth.py
hop3/commands/backup.py
hop3/commands/config.py
hop3/commands/git.py
hop3/commands/help.py
hop3/commands/misc.py
hop3/commands/services.py
hop3/commands/system.py
hop3/config.py
hop3/core/__init__.py
hop3/core/backup.py
hop3/core/credentials.py
hop3/core/env.py
hop3/core/events.py
hop3/core/git.py
hop3/core/hooks.py
hop3/core/hookspecs.py
hop3/core/plugins.py
hop3/core/protocols.py
hop3/core/runtime_registry.py
hop3/deployers/__init__.py
hop3/deployers/deployer.py
hop3/deployers/git_based_deployer.py
hop3/di/__init__.py
hop3/di/container.py
hop3/di/providers.py
hop3/lib/__init__.py
hop3/lib/archives.py
hop3/lib/backports.py
hop3/lib/config.py
hop3/lib/console.py
hop3/lib/datetime.py
hop3/lib/decorators.py
hop3/lib/freeze.py
hop3/lib/logging.py
hop3/lib/multi_tail.py
hop3/lib/path.py
hop3/lib/registry.py
hop3/lib/scanner.py
hop3/lib/settings.py
hop3/lib/sysinfo.py
hop3/lib/templating.py
hop3/lib/types.py
hop3/lib/util.py
hop3/orm/__init__.py
hop3/orm/addon_credential.py
hop3/orm/app.py
hop3/orm/backup.py
hop3/orm/env.py
hop3/orm/repositories.py
hop3/orm/revoked_token.py
hop3/orm/security.py
hop3/orm/session.py
hop3/platform/__init__.py
hop3/platform/certificates.py
hop3/plugins/__init__.py
hop3/plugins/build/__init__.py
hop3/plugins/build/language_toolchains/__init__.py
hop3/plugins/build/language_toolchains/plugin.py
hop3/plugins/build/local_build/__init__.py
hop3/plugins/build/local_build/builder.py
hop3/plugins/build/local_build/plugin.py
hop3/plugins/deploy/__init__.py
hop3_server-0.4.0b1.dist-info/WHEEL
hop3_server-0.4.0b1.dist-info/entry_points.txt
hop3_server-0.4.0b1.dist-info/METADATA
hop3_server-0.4.0b1.dist-info/RECORD
