Metadata-Version: 2.3
Name: hop3-server
Version: 0.4.0b1
Summary: Simple PaaS - Deploy and manage web applications on a single server
Author: Stefane Fermigier
Author-email: Stefane Fermigier <sf@abilian.com>
Requires-Dist: litestar[standard]>=2.18.0
Requires-Dist: attrs>=24.2
Requires-Dist: jinja2
Requires-Dist: itsdangerous>=2.0.0
Requires-Dist: pluggy~=1.4
Requires-Dist: dishka>=1.3.0
Requires-Dist: sqlalchemy~=2.0
Requires-Dist: advanced-alchemy>=0.21
Requires-Dist: alembic~=1.13
Requires-Dist: termcolor>=2.5.0
Requires-Dist: markdown>=3.5
Requires-Dist: cyclonedx-bom>=5.1.1
Requires-Dist: toml>=0.10.2
Requires-Dist: devtools
Requires-Dist: pyjwt>=2.8.0
Requires-Dist: bcrypt>=4.0.0
Requires-Dist: cryptography>=42.0.0
Requires-Dist: granian[reload]>=2.2.0
Requires-Dist: psycopg2-binary>=2.9.10
Requires-Dist: mysql-connector-python>=9.0.0
Requires-Dist: pyyaml>=6.0.3
Requires-Dist: python-multipart>=0.0.20
Requires-Dist: anyio
Requires-Dist: sniffio
Requires-Dist: uwsgi>=2.0.31
